{
    "swagger": "2.0",
    "info": {
        "contact": {}
    },
    "paths": {
        "/messages": {
            "get": {
                "description": "get all message list",
                "consumes": [
                    "application/json"
                ],
                "produces": [
                    "application/json"
                ],
                "tags": [
                    "Basic CRUD"
                ],
                "summary": "Get new messages",
                "responses": {
                    "200": {
                        "description": "OK",
                        "schema": {
                            "type": "array",
                            "items": {
                                "type": "string"
                            }
                        }
                    }
                }
            },
            "post": {
                "description": "get string by ID",
                "consumes": [
                    "application/json"
                ],
                "produces": [
                    "application/json"
                ],
                "tags": [
                    "Basic CRUD"
                ],
                "summary": "Create new messages",
                "responses": {
                    "200": {
                        "description": "OK",
                        "schema": {
                            "type": "array",
                            "items": {
                                "type": "string"
                            }
                        }
                    }
                }
            }
        },
        "/messages/{id}": {
            "get": {
                "description": "get all message list",
                "consumes": [
                    "application/json"
                ],
                "produces": [
                    "application/json"
                ],
                "tags": [
                    "Basic CRUD"
                ],
                "summary": "GetByID new messages",
                "responses": {
                    "200": {
                        "description": "OK",
                        "schema": {
                            "type": "array",
                            "items": {
                                "type": "string"
                            }
                        }
                    }
                }
            },
            "put": {
                "description": "Update messages by ID",
                "consumes": [
                    "application/json"
                ],
                "produces": [
                    "application/json"
                ],
                "tags": [
                    "Basic CRUD"
                ],
                "summary": "Update new messages",
                "responses": {
                    "200": {
                        "description": "OK",
                        "schema": {
                            "type": "array",
                            "items": {
                                "type": "string"
                            }
                        }
                    }
                }
            },
            "delete": {
                "description": "Delete string by ID",
                "consumes": [
                    "application/json"
                ],
                "produces": [
                    "application/json"
                ],
                "tags": [
                    "Basic CRUD"
                ],
                "summary": "Delete new messages",
                "responses": {
                    "200": {
                        "description": "OK",
                        "schema": {
                            "type": "array",
                            "items": {
                                "type": "string"
                            }
                        }
                    }
                }
            }
        }
    }
}